estory/__init__.py
estory/py.typed
estory-0.2.2.dist-info/entry_points.txt
estory-0.2.2.dist-info/LICENSE.md
estory-0.2.2.dist-info/WHEEL
estory-0.2.2.dist-info/METADATA
estory-0.2.2.dist-info/RECORD
