Metadata-Version: 2.1
Name: estory
Version: 0.2.2
Summary: Read from and write to event stores
Home-page: https://git.easter-eggs.org/bioneland/estory
License: GPL-3.0-or-later
Author: Tanguy Le Carrour
Author-email: tanguy@bioneland.org
Requires-Python: >=3.9,<4.0
Classifier: License :: OSI Approved :: GNU General Public License v3 or later (GPLv3+)
Classifier: Programming Language :: Python :: 3
Classifier: Programming Language :: Python :: 3.10
Classifier: Programming Language :: Python :: 3.9
Provides-Extra: mysql
Requires-Dist: PyMySQL (>=1.0.2,<2.0.0); extra == "mysql"
Requires-Dist: bles (>=0.3.0,<0.4.0)
Requires-Dist: blessql (>=0.1.3,<0.2.0)
Requires-Dist: typer (>=0.7.0,<0.8.0)
Project-URL: Repository, https://git.easter-eggs.org/bioneland/estory
